python_package_template_derived_test/__init__.py
python_package_template_derived_test/py.typed
python_package_template_derived_test/cli/__init__.py
python_package_template_derived_test/cli/main.py
python_package_qtemplate_derived_test-0.1.0.dist-info/LICENSE
python_package_qtemplate_derived_test-0.1.0.dist-info/METADATA
python_package_qtemplate_derived_test-0.1.0.dist-info/WHEEL
python_package_qtemplate_derived_test-0.1.0.dist-info/entry_points.txt
python_package_qtemplate_derived_test-0.1.0.dist-info/top_level.txt
python_package_qtemplate_derived_test-0.1.0.dist-info/RECORD
